valley/__init__.py
valley/checkpoint/__init__.py
valley/checkpoint/c2_model_loading.py
valley/checkpoint/vcheckpoint.py
valley/config/__init__.py
valley/config/config.py
valley/data/__init__.py
valley/data/datatype.py
valley/data/dataloader/__init__.py
valley/data/dataloader/base.py
valley/data/dataloader/builder.py
valley/data/dataset/__init__.py
valley/data/dataset/builder.py
valley/data/samplers/__init__.py
valley/data/samplers/distributed_sampler.py
valley/engine/__init__.py
valley/engine/builder.py
valley/engine/default.py
valley/engine/distribute.py
valley/engine/hooks.py
valley/engine/train_loop.py
valley/evaluator/__init__.py
valley/evaluator/base.py
valley/evaluator/builder.py
valley/evaluator/mnist_evaluation.py
valley/evaluator/testing.py
valley/model/__init__.py
valley/model/backbone/__init__.py
valley/model/backbone/backbone.py
valley/model/backbone/build.py
valley/model/backbone/lenet.py
valley/model/meta_arch/__init__.py
valley/model/meta_arch/build.py
valley/model/meta_arch/lenet_cls.py
valley/solver/__init__.py
valley/solver/build.py
valley/solver/lr_scheduler.py
valley/utils/__init__.py
valley/utils/comm.py
valley/utils/events.py
valley/utils/file_io.py
valley/utils/logger.py
valley/utils/plugin.py
canyon-1.0.dist-info/LICENSE
canyon-1.0.dist-info/METADATA
canyon-1.0.dist-info/WHEEL
canyon-1.0.dist-info/top_level.txt
canyon-1.0.dist-info/RECORD
